aa_discord_announcements/__init__.py
aa_discord_announcements/admin.py
aa_discord_announcements/app_settings.py
aa_discord_announcements/apps.py
aa_discord_announcements/auth_hooks.py
aa_discord_announcements/constants.py
aa_discord_announcements/forms.py
aa_discord_announcements/models.py
aa_discord_announcements/providers.py
aa_discord_announcements/urls.py
aa_discord_announcements/views.py
aa_discord_announcements/helper/announcement_context.py
aa_discord_announcements/helper/discord_webhook.py
aa_discord_announcements/locale/django.pot
aa_discord_announcements/locale/cs_CZ/LC_MESSAGES/django.mo
aa_discord_announcements/locale/cs_CZ/LC_MESSAGES/django.po
aa_discord_announcements/locale/de/LC_MESSAGES/django.mo
aa_discord_announcements/locale/de/LC_MESSAGES/django.po
aa_discord_announcements/locale/es/LC_MESSAGES/django.mo
aa_discord_announcements/locale/es/LC_MESSAGES/django.po
aa_discord_announcements/locale/fr_FR/LC_MESSAGES/django.mo
aa_discord_announcements/locale/fr_FR/LC_MESSAGES/django.po
aa_discord_announcements/locale/it_IT/LC_MESSAGES/django.mo
aa_discord_announcements/locale/it_IT/LC_MESSAGES/django.po
aa_discord_announcements/locale/ja/LC_MESSAGES/django.mo
aa_discord_announcements/locale/ja/LC_MESSAGES/django.po
aa_discord_announcements/locale/ko_KR/LC_MESSAGES/django.mo
aa_discord_announcements/locale/ko_KR/LC_MESSAGES/django.po
aa_discord_announcements/locale/nl_NL/LC_MESSAGES/django.mo
aa_discord_announcements/locale/nl_NL/LC_MESSAGES/django.po
aa_discord_announcements/locale/pl_PL/LC_MESSAGES/django.mo
aa_discord_announcements/locale/pl_PL/LC_MESSAGES/django.po
aa_discord_announcements/locale/ru/LC_MESSAGES/django.mo
aa_discord_announcements/locale/ru/LC_MESSAGES/django.po
aa_discord_announcements/locale/sk/LC_MESSAGES/django.mo
aa_discord_announcements/locale/sk/LC_MESSAGES/django.po
aa_discord_announcements/locale/uk/LC_MESSAGES/django.mo
aa_discord_announcements/locale/uk/LC_MESSAGES/django.po
aa_discord_announcements-2.7.1.dist-info/METADATA
aa_discord_announcements-2.7.1.dist-info/WHEEL
aa_discord_announcements-2.7.1.dist-info/licenses/LICENSE
aa_discord_announcements-2.7.1.dist-info/RECORD
